monkeypatcher/__init__.py
monkeypatcher/patch.py
monkeypatcher-1.2.0.dist-info/DESCRIPTION.rst
monkeypatcher-1.2.0.dist-info/METADATA
monkeypatcher-1.2.0.dist-info/RECORD
monkeypatcher-1.2.0.dist-info/WHEEL
monkeypatcher-1.2.0.dist-info/metadata.json
monkeypatcher-1.2.0.dist-info/top_level.txt
