Metadata-Version: 2.0
Name: monkeypatcher
Version: 1.2.0
Summary: A python monkey-patching library
Home-page: https://github.com/iki/monkeypatch
Author: Thomas Vagner
Author-email: vagner.thomas@yandex.com
License: MIT
Keywords: monkeypatch testing mock
Platform: UNKNOWN
Classifier: Development Status :: 5 - Production/Stable
Classifier: Intended Audience :: Developers
Classifier: License :: OSI Approved :: MIT License
Classifier: Programming Language :: Python :: 2.7
Requires-Dist: requests
